<?xml version="1.0" encoding="UTF-8"?>
<node>
<version>6</version>
<dict>
  <key>expanded</key><true/>
  <key>title</key><string>Cheet Sheet Compilations</string>
  <key>nodeid</key><string>ca17c75b-fd94-471f-8e0a-d54e3ae1f2b9</string>
  <key>modified_time</key><integer>1516391136</integer>
  <key>version</key><integer>6</integer>
  <key>content_type</key><string>text/xhtml+xml</string>
  <key>created_time</key><integer>1516294712</integer>
  <key>info_sort_dir</key><integer>1</integer>
  <key>order</key><integer>1</integer>
  <key>info_sort</key><string>order</string>
</dict>
</node>
