<?xml version="1.0" encoding="UTF-8"?>
<node>
<version>6</version>
<dict>
  <key>title</key><string>List</string>
  <key>nodeid</key><string>cba3fea3-177a-4757-a028-3e4b79d6ca92</string>
  <key>modified_time</key><integer>1508863965</integer>
  <key>version</key><integer>6</integer>
  <key>content_type</key><string>text/xhtml+xml</string>
  <key>created_time</key><integer>1508765419</integer>
  <key>info_sort_dir</key><integer>1</integer>
  <key>order</key><integer>0</integer>
  <key>info_sort</key><string>order</string>
</dict>
</node>
